termina/__init__.py
termina/auth/__init__.py
termina/auth/client.py
termina/auth/raw_client.py
termina/base_client.py
termina/benchmark/__init__.py
termina/benchmark/client.py
termina/benchmark/raw_client.py
termina/benchmark/types/__init__.py
termina/benchmark/types/benchmark_get_combined_time_series_request_user_type.py
termina/benchmark/types/benchmark_get_combined_time_series_response_item_value.py
termina/benchmark/types/benchmark_get_deal_benchmark_quantiles_request_user_type.py
termina/benchmark/types/benchmark_get_deal_benchmark_quantiles_response_item_value.py
termina/benchmark/types/benchmark_get_deal_benchmark_tradeoff_at_scale_request_user_type.py
termina/benchmark/types/benchmark_get_quantiles_request_user_type.py
termina/benchmark/types/benchmark_get_quantiles_response_item_value.py
termina/benchmark/types/benchmark_get_scaling_request_user_type.py
termina/benchmark/types/benchmark_get_time_series_endpoint_request_user_type.py
termina/benchmark/types/benchmark_get_time_series_endpoint_response_value.py
termina/benchmark/types/benchmark_get_tradeoff_at_scale_request_user_type.py
termina/chat/__init__.py
termina/chat/client.py
termina/client.py
termina/company/__init__.py
termina/company/client.py
termina/company/raw_client.py
termina/core/__init__.py
termina/core/api_error.py
termina/core/client_wrapper.py
termina/core/datetime_utils.py
termina/core/file.py
termina/core/force_multipart.py
termina/core/http_client.py
termina/core/http_response.py
termina/core/jsonable_encoder.py
termina/core/oauth_token_provider.py
termina/core/pydantic_utilities.py
termina/core/query_encoder.py
termina/core/remove_none_from_dict.py
termina/core/request_options.py
termina/core/serialization.py
termina/deal/__init__.py
termina/deal/client.py
termina/deal/raw_client.py
termina/deal/types/__init__.py
termina/deal/types/metadata.py
termina/environment.py
termina/errors/__init__.py
termina/errors/content_too_large_error.py
termina/errors/unprocessable_entity_error.py
termina-0.2.3.dist-info/METADATA
termina-0.2.3.dist-info/WHEEL
termina-0.2.3.dist-info/RECORD
